gtp.py
setup.py
pygtp.egg-info/PKG-INFO
pygtp.egg-info/SOURCES.txt
pygtp.egg-info/dependency_links.txt
pygtp.egg-info/top_level.txt