Metadata-Version: 1.1
Name: pygtp
Version: 0.4
Summary: Python library for Go Text Protocol controllers and engines
Home-page: http://github.com/jtauber/gtp
Author: James Tauber
Author-email: jtauber@jtauber.com
License: MIT
Platform: UNKNOWN
Classifier: Development Status :: 3 - Alpha
Classifier: License :: OSI Approved :: MIT License
Classifier: Programming Language :: Python :: 2.7
Classifier: Programming Language :: Python :: 3.3
Classifier: Programming Language :: Python :: 3.4
Classifier: Programming Language :: Python :: 3.5
Classifier: Programming Language :: Python :: 3.6
Classifier: Topic :: Games/Entertainment :: Board Games
Classifier: Topic :: Utilities
